lesecret/__init__.py
lesecret/main.py
lesecret-0.0.5.dist-info/METADATA
lesecret-0.0.5.dist-info/WHEEL
lesecret-0.0.5.dist-info/entry_points.txt
lesecret-0.0.5.dist-info/licenses/LICENSE
lesecret-0.0.5.dist-info/RECORD
